latticejson/__about__.py
latticejson/__init__.py
latticejson/cli.py
latticejson/convert.py
latticejson/elegant.lark
latticejson/exceptions.py
latticejson/format.py
latticejson/io.py
latticejson/madx.lark
latticejson/map.json
latticejson/migrate.py
latticejson/parse.py
latticejson/schema.json
latticejson/utils.py
latticejson/validate.py
LatticeJSON-0.1.6.dist-info/LICENSE
LatticeJSON-0.1.6.dist-info/METADATA
LatticeJSON-0.1.6.dist-info/WHEEL
LatticeJSON-0.1.6.dist-info/entry_points.txt
LatticeJSON-0.1.6.dist-info/top_level.txt
LatticeJSON-0.1.6.dist-info/RECORD
