Metadata-Version: 2.1
Name: LatticeJSON
Version: 0.1.6
Summary: A JSON based lattice file format
Home-page: https://github.com/andreasfelix/latticejson
Author: Felix Andreas
License: GNU General Public License v3.0
Platform: UNKNOWN
Classifier: Development Status :: 3 - Alpha
Classifier: Intended Audience :: Science/Research
Classifier: License :: OSI Approved :: GNU General Public License v3 (GPLv3)
Classifier: Programming Language :: Python :: 3.6
Classifier: Programming Language :: Python :: 3.7
Classifier: Programming Language :: Python :: 3.8
Classifier: Programming Language :: Python :: Implementation :: CPython
Classifier: Programming Language :: Python :: Implementation :: PyPy
Classifier: Topic :: Scientific/Engineering
Requires-Python: >=3.6
Requires-Dist: click (>=7.0)
Requires-Dist: fastjsonschema
Requires-Dist: lark-parser
Requires-Dist: packaging
